Workbook

Sheet Assumptions
A1: Loan Default Risk - Profit Model Assumptions
A3: Margin earned on a repaid loan (% of loan amount) | B3: 0.15
A4: Loss on a defaulted loan (% of loan amount) | B4: 0.6
A5: Break-even default rate (reject above this) | B5: =B3/(B3+B4) -> 0.2
A7: Notes
A8: Edit only the yellow cells. Everything else recalculates.
A9: Margin and loss are my own assumptions, not real bank figures.
A10: Band data comes from risk_bands.csv produced in notebook Block 18
A11: Money is in the dataset's own currency units; profit shown in millions.

Sheet Bands
A1: Profit by Risk Band
A3: Band | B3: Customers | C3: Default rate | D3: Avg loan | E3: Good customers | F3: Bad customers | G3: Interest earned | H3: Default loss | I3: Net profit (M) | J3: Action
A4: Low | B4: 36901 | C4: 0.0328 | D4: 628988 | E4: =B4*(1-C4) -> 35690.647 | F4: =B4*C4 -> 1210.3528 | G4: =E4*D4*Assumptions!$B$3 -> 3.3673483e+09 | H4: =F4*D4*Assumptions!$B$4 -> 4.5677843e+08 | I4: =(G4-H4)/1000000 -> 2910.5699 | J4: Approve at standard rate
A5: Medium | B5: 12301 | C5: 0.0913 | D5: 579889 | E5: =B5*(1-C5) -> 11177.919 | F5: =B5*C5 -> 1123.0813 | G5: =E5*D5*Assumptions!$B$3 -> 9.7229281e+08 | H5: =F5*D5*Assumptions!$B$4 -> 3.907575e+08 | I5: =(G5-H5)/1000000 -> 581.53532 | J5: Approve and monitor
A6: High | B6: 7300 | C6: 0.1525 | D6: 534835 | E6: =B6*(1-C6) -> 6186.75 | F6: =B6*C6 -> 1113.25 | G6: =E6*D6*Assumptions!$B$3 -> 4.9633357e+08 | H6: =F6*D6*Assumptions!$B$4 -> 3.5724304e+08 | I6: =(G6-H6)/1000000 -> 139.09053 | J6: Higher rate, lower limit or manual review
A7: Reject | B7: 5001 | C7: 0.3037 | D7: 503359 | E7: =B7*(1-C7) -> 3482.1963 | F7: =B7*C7 -> 1518.8037 | G7: =E7*D7*Assumptions!$B$3 -> 2.6291923e+08 | H7: =F7*D7*Assumptions!$B$4 -> 4.5870211e+08 | I7: =(G7-H7)/1000000 -> -195.78288 | J7: Decline
A9: Summary
A10: Profit if everyone is approved (M) | I10: =SUM(I4:I7) -> 3435.4129
A11: Profit with model cut-off, Reject band declined (M) | I11: =SUM(I4:I6) -> 3631.1957
A12: Gain from using the model (M) | I12: =I11-I10 -> 195.78288
A13: Gain as % of approve-everyone profit | I13: =IF(I10=0,0,I12/I10) -> 0.056989622
A14: Share of customers approved | I14: =SUM(B4:B6)/SUM(B4:B7) -> 0.91868689
A15: Default rate of approved customers | I15: =SUM(F4:F6)/SUM(B4:B6) -> 0.061001099
A16: Default rate of rejected customers | I16: =F7/B7 -> 0.3037
A18: Inputs in blue come from notebook Block 18 (risk_bands.csv). Excel uses band-average loan size, so totals are close to, but not exactly equal to, the customer-level notebook profit.

Sheet Sensitivity
A1: Sensitivity to the loss assumption
A3: Table 1: fixed bands (approve Low, Medium, High) - live formulas
A4: Loss per bad loan | B4: Profit: approve everyone (M) | C4: Profit: model cut-off (M) | D4: Gain (M) | E4: Gain %
A5: 0.4 | B5: =(SUMPRODUCT(Bands!$E$4:$E$7,Bands!$D$4:$D$7)*Assumptions!$B$3-SUMPRODUCT(Bands!$F$4:$F$7,Bands!$D$4:$D$7)*A5)/1000000 -> 3989.9065 | C5: =(SUMPRODUCT(Bands!$E$4:$E$6,Bands!$D$4:$D$6)*Assumptions!$B$3-SUMPRODUCT(Bands!$F$4:$F$6,Bands!$D$4:$D$6)*A5)/1000000 -> 4032.7887 | D5: =C5-B5 -> 42.882178 | E5: =IF(B5=0,0,D5/B5) -> 0.010747665
A6: 0.6 | B6: =(SUMPRODUCT(Bands!$E$4:$E$7,Bands!$D$4:$D$7)*Assumptions!$B$3-SUMPRODUCT(Bands!$F$4:$F$7,Bands!$D$4:$D$7)*A6)/1000000 -> 3435.4129 | C6: =(SUMPRODUCT(Bands!$E$4:$E$6,Bands!$D$4:$D$6)*Assumptions!$B$3-SUMPRODUCT(Bands!$F$4:$F$6,Bands!$D$4:$D$6)*A6)/1000000 -> 3631.1957 | D6: =C6-B6 -> 195.78288 | E6: =IF(B6=0,0,D6/B6) -> 0.056989622
A7: 0.8 | B7: =(SUMPRODUCT(Bands!$E$4:$E$7,Bands!$D$4:$D$7)*Assumptions!$B$3-SUMPRODUCT(Bands!$F$4:$F$7,Bands!$D$4:$D$7)*A7)/1000000 -> 2880.9192 | C7: =(SUMPRODUCT(Bands!$E$4:$E$6,Bands!$D$4:$D$6)*Assumptions!$B$3-SUMPRODUCT(Bands!$F$4:$F$6,Bands!$D$4:$D$6)*A7)/1000000 -> 3229.6027 | D7: =C7-B7 -> 348.68358 | E7: =IF(B7=0,0,D7/B7) -> 0.12103206
A8: 1 | B8: =(SUMPRODUCT(Bands!$E$4:$E$7,Bands!$D$4:$D$7)*Assumptions!$B$3-SUMPRODUCT(Bands!$F$4:$F$7,Bands!$D$4:$D$7)*A8)/1000000 -> 2326.4255 | C8: =(SUMPRODUCT(Bands!$E$4:$E$6,Bands!$D$4:$D$6)*Assumptions!$B$3-SUMPRODUCT(Bands!$F$4:$F$6,Bands!$D$4:$D$6)*A8)/1000000 -> 2828.0098 | D8: =C8-B8 -> 501.58428 | E8: =IF(B8=0,0,D8/B8) -> 0.21560299
A11: Table 2: best cut-off re-chosen for each loss value - results from notebook Block 19 (hardcoded)
A12: Loss per bad loan | B12: Share approved | C12: Profit: approve everyone (M) | D12: Profit: best cut-off (M) | E12: Gain (M) | F12: Gain %
A13: 0.4 | B13: 0.947 | C13: 3988.3 | D13: 4057.5 | E13: =D13-C13 -> 69.2 | F13: =IF(C13=0,0,E13/C13) -> 0.017350751
A14: 0.6 | B14: 0.919 | C14: 3433.2 | D14: 3636.8 | E14: =D14-C14 -> 203.6 | F14: =IF(C14=0,0,E14/C14) -> 0.059303274
A15: 0.8 | B15: 0.876 | C15: 2878.2 | D15: 3276.3 | E15: =D15-C15 -> 398.1 | F15: =IF(C15=0,0,E15/C15) -> 0.13831561
A16: 1 | B16: 0.833 | C16: 2323.1 | D16: 2950.9 | E16: =D16-C16 -> 627.8 | F16: =IF(C16=0,0,E16/C16) -> 0.27024235
A18: Table 1 keeps the Reject band fixed, so its gain is only approximate. Table 2 re-picks the cut-off per loss value at customer level in the notebook, so it is the one to quote.
